LICENSE
MANIFEST.in
README.rst
setup.py
fp/__init__.py
fp/missing_six.py
fp.egg-info/PKG-INFO
fp.egg-info/SOURCES.txt
fp.egg-info/dependency_links.txt
fp.egg-info/entry_points.txt
fp.egg-info/not-zip-safe
fp.egg-info/requires.txt
fp.egg-info/top_level.txt
fp/collections/__init__.py
fp/monads/__init__.py
fp/monads/either.py
fp/monads/iomonad.py
fp/monads/maybe.py
fp/monads/monad.py