Metadata-Version: 1.1
Name: fp
Version: 0.2
Summary: All the good stuff from Functional Programming
Home-page: https://fp.readthedocs.org/en/latest/
Author: Eric Moritz
Author-email: eric@themoritzfamily.com
License: BSD
Platform: UNKNOWN
Classifier: Development Status :: 3 - Alpha
Classifier: Intended Audience :: Developers
Classifier: License :: OSI Approved :: BSD License
Classifier: Programming Language :: Python :: 2.6
Classifier: Programming Language :: Python :: 2.7
Classifier: Programming Language :: Python :: 3.2
Classifier: Programming Language :: Python :: 3.3
